{
  "version": "1.2.6",
  "cards": [
    {"term": "Pull request", "hint": "Žádost o přijetí tvých změn kódu do hlavní větve v Gitlabu", "category": "describe", "group_name": "IT", "difficulty": 1, "points": 1},
    {"term": "Merge conflict", "hint": "Situace v Gitu, kdy dvě větve změnily stejný řádek a Git neví, co nechat", "category": "describe", "group_name": "IT", "difficulty": 2, "points": 1},
    {"term": "Docker container", "hint": "Izolované prostředí, kde běží aplikace nezávisle na hostitelském systému", "category": "describe", "group_name": "IT", "difficulty": 2, "points": 1},
    {"term": "CI/CD pipeline", "hint": "Automatizovaný proces, který po každém commitu spustí testy a nasadí aplikaci", "category": "describe", "group_name": "IT", "difficulty": 2, "points": 1},
    {"term": "Refactoring", "hint": "Přepisování kódu, aby byl čistší a čitelnější, aniž by se změnilo jeho chování", "category": "describe", "group_name": "IT", "difficulty": 2, "points": 1},
    {"term": "Dependency injection", "hint": "Návrhový vzor, kdy objekt dostane své závislosti zvenčí místo aby si je vytvářel sám", "category": "describe", "group_name": "IT", "difficulty": 3, "points": 2},
    {"term": "Composer", "hint": "Správce závislostí pro PHP projekty, soubor composer.json říká, co projekt potřebuje", "category": "describe", "group_name": "IT", "difficulty": 2, "points": 1},
    {"term": "Vue komponenta", "hint": "Znovupoužitelný kus UI ve Vue.js s vlastní šablonou, logikou a styly v jednom souboru", "category": "describe", "group_name": "IT", "difficulty": 2, "points": 1},
    {"term": "Reaktivita ve Vue", "hint": "Mechanismus, kdy se UI automaticky překreslí při změně dat v ref nebo reactive", "category": "describe", "group_name": "IT", "difficulty": 3, "points": 2},
    {"term": "PHPUnit test", "hint": "Automatický test v PHP, který ověřuje, zda funkce vrací správný výsledek", "category": "describe", "group_name": "IT", "difficulty": 2, "points": 1},
    {"term": "Gherkin scénář", "hint": "Popis testu v přirozeném jazyce pomocí klíčových slov Given, When, Then", "category": "describe", "group_name": "IT", "difficulty": 2, "points": 1},
    {"term": "OpenSearch index", "hint": "Datová struktura v OpenSearch, která umožňuje rychle vyhledávat ve velkém množství dokumentů", "category": "describe", "group_name": "IT", "difficulty": 3, "points": 2},
    {"term": "Git rebase", "hint": "Přesun nebo sloučení série commitů na nový základ větve, historie vypadá lineárně", "category": "describe", "group_name": "IT", "difficulty": 3, "points": 2},
    {"term": "Jira sprint", "hint": "Časově ohraničené období, typicky dva týdny, kdy tým pracuje na vybraných úkolech", "category": "describe", "group_name": "IT", "difficulty": 1, "points": 1},
    {"term": "Playwright test", "hint": "Automatizovaný end-to-end test, který ovládá prohlížeč jako skutečný uživatel", "category": "describe", "group_name": "IT", "difficulty": 2, "points": 1},
    {"term": "Docker Compose", "hint": "Nástroj pro spuštění více kontejnerů najednou – databáze, backend, frontend jedním příkazem", "category": "describe", "group_name": "IT", "difficulty": 2, "points": 1},
    {"term": "Feature flag", "hint": "Přepínač v kódu, který zapne nebo vypne funkci bez nasazení nové verze", "category": "describe", "group_name": "IT", "difficulty": 2, "points": 1},
    {"term": "Code review", "hint": "Kolegův pohled na tvůj kód před mergem – hledá chyby, navrhuje zlepšení", "category": "describe", "group_name": "IT", "difficulty": 1, "points": 1},
    {"term": "Regression test", "hint": "Test ověřující, že opravená chyba se nevrátila a nové změny nerozbily starou funkcionalitu", "category": "describe", "group_name": "IT", "difficulty": 2, "points": 1},
    {"term": "Aggregation v OpenSearch", "hint": "Dotaz, který data nejen hledá, ale rovnou počítá statistiky – průměr, součet, histogram", "category": "describe", "group_name": "IT", "difficulty": 3, "points": 2},
    {"term": "Git flow", "hint": "Větvící strategie s main, develop, feature, release a hotfix větvemi", "category": "draw", "group_name": "IT", "difficulty": 3, "points": 2},
    {"term": "Architektura mikroslužeb", "hint": "Systém rozdělený do malých nezávislých služeb, každá dělá jednu věc a komunikuje přes API", "category": "draw", "group_name": "IT", "difficulty": 3, "points": 2},
    {"term": "Docker síť kontejnerů", "hint": "Schéma jak spolu mluví kontejnery – frontend, backend, databáze ve vlastní síti", "category": "draw", "group_name": "IT", "difficulty": 3, "points": 2},
    {"term": "Životní cyklus Vue komponenty", "hint": "Diagram fází od vytvoření přes mounted až po destroyed", "category": "draw", "group_name": "IT", "difficulty": 3, "points": 2},
    {"term": "CI/CD pipeline diagram", "hint": "Schéma kroků: commit → build → test → deploy s šipkami a fázemi", "category": "draw", "group_name": "IT", "difficulty": 2, "points": 1},
    {"term": "Jira kanban board", "hint": "Tabule se sloupci To Do, In Progress, In Review, Done a kartičkami úkolů", "category": "draw", "group_name": "IT", "difficulty": 1, "points": 1},
    {"term": "ER diagram databáze", "hint": "Schéma tabulek s jejich vztahy – jeden k mnoha, mnoho k mnoha", "category": "draw", "group_name": "IT", "difficulty": 2, "points": 1},
    {"term": "Playwright test flow", "hint": "Diagram kroků: otevři prohlížeč → naviguj → klikni → ověř výsledek", "category": "draw", "group_name": "IT", "difficulty": 2, "points": 1},
    {"term": "Stav Vuex / Pinia store", "hint": "Schéma centrálního úložiště dat – state, getters, actions a jak k nim přistupují komponenty", "category": "draw", "group_name": "IT", "difficulty": 3, "points": 2},
    {"term": "REST API endpointy", "hint": "Tabulka nebo strom URL adres s metodami GET, POST, PUT, DELETE", "category": "draw", "group_name": "IT", "difficulty": 2, "points": 1},
    {"term": "Pyramida testů", "hint": "Trojúhelník unit testů dole, integračních uprostřed a E2E nahoře", "category": "draw", "group_name": "IT", "difficulty": 2, "points": 1},
    {"term": "PHP namespace strom", "hint": "Hierarchie složek a tříd organizovaná jako větve stromu", "category": "draw", "group_name": "IT", "difficulty": 2, "points": 1},
    {"term": "OpenSearch cluster", "hint": "Schéma uzlů – master node, data nodes a jak mezi nimi proudí data", "category": "draw", "group_name": "IT", "difficulty": 3, "points": 2},
    {"term": "Scrum sprint cyklus", "hint": "Kruhový diagram: planning → daily → review → retro → další sprint", "category": "draw", "group_name": "IT", "difficulty": 2, "points": 1},
    {"term": "Debugování kódu – hledání bugu", "hint": "Zírání do monitoru, škrábání hlavy, breakpoint po breakpointu, úleva při nalezení", "category": "mime", "group_name": "IT", "difficulty": 1, "points": 1},
    {"term": "Git push --force", "hint": "Stisknout enter, okamžitá lítost, zděšení co jsem to udělal kolegům", "category": "mime", "group_name": "IT", "difficulty": 2, "points": 1},
    {"term": "Standup meeting", "hint": "Každý stojí, říká co dělal, co bude dělat a kde je blokován – rychle!", "category": "mime", "group_name": "IT", "difficulty": 1, "points": 1},
    {"term": "Merge conflict řešení", "hint": "Zoufalé porovnávání dvou verzí kódu, mazání šipek a znaků, modlení ať to funguje", "category": "mime", "group_name": "IT", "difficulty": 2, "points": 1},
    {"term": "Deploy v pátek odpoledne", "hint": "Stisknout tlačítko nasazení, pak nervózně sledovat logy a pomalu couvat ke dveřím", "category": "mime", "group_name": "IT", "difficulty": 1, "points": 1},
    {"term": "Playwright klikání na elementy", "hint": "Ukazovat na obrazovku, klikat ve vzduchu, čekat na načtení, znovu klikat", "category": "mime", "group_name": "IT", "difficulty": 2, "points": 1},
    {"term": "Code review komentáře", "hint": "Číst kód, kroutit hlavou, psát poznámky, gestikulovat proč tohle vůbec tak je", "category": "mime", "group_name": "IT", "difficulty": 2, "points": 1},
    {"term": "Docker build čekání", "hint": "Spustit příkaz, zaklopit se, koukat na loading, odejít pro kávu, vrátit se, stále běží", "category": "mime", "group_name": "IT", "difficulty": 1, "points": 1},
    {"term": "Retrospektiva – co nás štvalo", "hint": "Tým postupně lepí sticky notes na tabuli a každý si odplivne nad tím, co ho trápilo", "category": "mime", "group_name": "IT", "difficulty": 2, "points": 1},
    {"term": "Odhad story points", "hint": "Každý drží kartu s číslem, na signál všichni otočí – chaos čísel, diskuze proč každý dal jinak", "category": "mime", "group_name": "IT", "difficulty": 2, "points": 1},
    {"term": "PHP Fatal Error v produkci", "hint": "Klidná práce, notifikace, zděšení, frenetické psaní, pot, hotfix, vydechnutí", "category": "mime", "group_name": "IT", "difficulty": 2, "points": 1},
    {"term": "Vysvětlování bugu zákazníkovi", "hint": "Gestikulovat, zjednodušovat, sledovat jak nepochopení roste, nakonec říct že to opravíme", "category": "mime", "group_name": "IT", "difficulty": 2, "points": 1},
    {"term": "Čekání na pipeline", "hint": "Stisknout merge, otevřít jiný tab, zívat, obnovovat stránku, 12 minut čekání", "category": "mime", "group_name": "IT", "difficulty": 1, "points": 1},
    {"term": "Gherkin scénář psaní", "hint": "Přemýšlet, psát Given, škrtnout, přepsat, číst nahlas, gestikulovat jestli to dává smysl", "category": "mime", "group_name": "IT", "difficulty": 3, "points": 2},
    {"term": "Pair programming", "hint": "Dva lidé u jednoho počítače – jeden píše, druhý kouká a radí, střídají se", "category": "mime", "group_name": "IT", "difficulty": 1, "points": 1},
    {"term": "Test prochází lokálně ale ne v CI", "hint": "Doma zelená, v pipeline červená – zírání, krčení ramen, „u mě to funguje", "category": "mime", "group_name": "IT", "difficulty": 2, "points": 1}
  ]
}
